pydatrie
