Metadata-Version: 2.1
Name: pydatrie
Version: 0.2
Summary: Pure Python implementation of DARTS (Double ARray Trie System)
Home-page: https://github.com/hyunwoongko/pydatrie
Author: Kevin Ko
Author-email: kevin.ko@tunib.ai
License: Apache 2.0 License
Platform: any
Requires-Python: >=3
